strcolred/__init__.py
strcolred/test.py
strcolred-2.1.dist-info/METADATA
strcolred-2.1.dist-info/WHEEL
strcolred-2.1.dist-info/top_level.txt
strcolred-2.1.dist-info/RECORD
