Metadata-Version: 2.1
Name: strcolred
Version: 2.1
Summary: Python terminal colour library
Author-email: john.lesure@gmail.com
License: Eclipse Public License 2.0
